{
  "users": [
    {
      "id": "22ddd4b7-228d-4ee9-89df-c5595fecc8b8",
      "name": "Kareem",
      "username": "kcasserly0",
      "email": "kmoakes0@scientificamerican.com",
      "phone": "1844107359"
    },
    {
      "id": "ccf460f0-761e-4f63-8023-3d518f5e08f8",
      "name": "Mead",
      "username": "mkovelmann1",
      "email": "mheningham1@thetimes.co.uk",
      "phone": "5212961295"
    },
    {
      "id": "bf29f358-7783-442a-8aa5-10306b817802",
      "name": "Renaud",
      "username": "rpinchbeck2",
      "email": "rmeineken2@chron.com",
      "phone": "8364381743"
    },
    {
      "id": "90eacb8e-b414-4ecf-ac31-0d6d18e4dcfe",
      "name": "Rennie",
      "username": "rjeavon3",
      "email": "rfrankland3@mozilla.com",
      "phone": "3474496459"
    },
    {
      "id": "26a8759f-9fc2-49a9-9b74-98fd8376fba0",
      "name": "Jessalin",
      "username": "jlocard4",
      "email": "jbrunsden4@narod.ru",
      "phone": "8264621346"
    },
    {
      "id": "7e106d00-b93b-43c9-9882-9ebcf4e94a0b",
      "name": "Vic",
      "username": "vdaly5",
      "email": "vciccone5@cafepress.com",
      "phone": "1452428408"
    },
    {
      "id": "9e681575-6f36-4296-8c5c-8fc324879912",
      "name": "Meghan",
      "username": "mthaxter6",
      "email": "mbartkowiak6@1und1.de",
      "phone": "6338061494"
    },
    {
      "id": "96e3898c-1ee2-49b9-ae3b-19dd8456e9f3",
      "name": "Filia",
      "username": "ffulop8",
      "email": "fleah8@163.com",
      "phone": "8263042138"
    },
    {
      "id": "8ca9b770-5af1-4047-b5f7-e0e2b387577d",
      "name": "Darda",
      "username": "dbinnes9",
      "email": "dkiley9@mail.ru",
      "phone": "8177150817"
    },
    {
      "id": "a3440390-692e-4f2e-b34a-442684ce9e02",
      "name": "Manuel",
      "username": "msabatera",
      "email": "mtorbarda@apache.org",
      "phone": "3554089148"
    },
    {
      "id": "d8850902-41c1-4804-af13-d0ad5bdda89b",
      "name": "Marlo",
      "username": "mabellb",
      "email": "mallainb@desdev.cn",
      "phone": "7307438922"
    },
    {
      "id": "8b4f804d-352a-4640-9764-3859ff925f66",
      "name": "Marnie",
      "username": "mstarrsc",
      "email": "mloffillc@nifty.com",
      "phone": "5625279375"
    },
    {
      "id": "463d93a3-1b23-4341-9be4-91e824e8bc28",
      "name": "Dunn",
      "username": "draind",
      "email": "dmacpeaked@baidu.com",
      "phone": "3639007247"
    },
    {
      "id": "9524d79a-15b3-4ac5-867a-f20384f78a84",
      "name": "Avram",
      "username": "ashrubshalle",
      "email": "acarolinee@phoca.cz",
      "phone": "2425262398"
    },
    {
      "id": "35465075-496f-4c65-8cbe-0a58f38d72e9",
      "name": "Annette",
      "username": "avassf",
      "email": "abusseyf@cyberchimps.com",
      "phone": "3313272049"
    },
    {
      "id": "35d3a362-0f14-45a0-abe4-a3a65dcb3261",
      "name": "Joanie",
      "username": "jcotgroveg",
      "email": "jshepheardg@google.fr",
      "phone": "5089690664"
    },
    {
      "id": "226be82e-e87a-4ef5-b719-264e5b4a68ca",
      "name": "Olympie",
      "username": "oginnih",
      "email": "obernasekh@mtv.com",
      "phone": "9434746690"
    },
    {
      "id": "a64e58df-3253-40d8-b437-259e6f5b8bd1",
      "name": "Opal",
      "username": "ogillorani",
      "email": "omarryatti@squarespace.com",
      "phone": "3577950690"
    },
    {
      "id": "04cb37cb-79c3-40f5-b86b-5f5df7e6f861",
      "name": "Jorrie",
      "username": "jgeroj",
      "email": "jcordreyj@bing.com",
      "phone": "4103371144"
    },
    {
      "id": "3242514f-7b2c-4de4-a120-ea3580a41edc",
      "name": "Findlay",
      "username": "fpetrazzik",
      "email": "fmeiklemk@army.mil",
      "phone": "1695154663"
    },
    {
      "id": "281fbfe3-8d69-4dd0-ba86-87be33390056",
      "name": "Dimitri",
      "username": "dmarquesel",
      "email": "dloraitl@timesonline.co.uk",
      "phone": "6513365393"
    },
    {
      "id": "85686641-6edb-4817-b654-cf2d3a63ad65",
      "name": "Lemmie",
      "username": "losgordbym",
      "email": "lnuzztim@uiuc.edu",
      "phone": "3379050289"
    },
    {
      "id": "a8e141c1-fbfe-4fd0-aaea-36199dafb7b1",
      "name": "Lyn",
      "username": "llumbyn",
      "email": "lpablon@addtoany.com",
      "phone": "1802078104"
    },
    {
      "id": "64affb9e-43ee-4467-bb11-8a61f5917d81",
      "name": "Lyon",
      "username": "lgransdeno",
      "email": "lheijneno@hugedomains.com",
      "phone": "6533041643"
    },
    {
      "id": "780854b0-5e9b-4bb5-acb0-776c2db43087",
      "name": "Elisha",
      "username": "eattwoolp",
      "email": "ewilsep@nsw.gov.au",
      "phone": "7115410020"
    },
    {
      "id": "966b883f-1ee6-4292-80bc-6df1287f574a",
      "name": "Lester",
      "username": "lbeiningq",
      "email": "ltwiningq@prweb.com",
      "phone": "5189063748"
    },
    {
      "id": "2f9b7af2-cea7-4411-8c40-47e29cc07b5c",
      "name": "Maryellen",
      "username": "mschankelborgr",
      "email": "monionsr@latimes.com",
      "phone": "8071143715"
    },
    {
      "id": "c421e12c-d69a-40a4-8cc4-5c1151ade9c2",
      "name": "Freddie",
      "username": "fgells",
      "email": "ffaunchs@parallels.com",
      "phone": "4295214675"
    },
    {
      "id": "f127e34e-d190-47f8-a077-1deea83660e4",
      "name": "Tyson",
      "username": "tklimschaku",
      "email": "tcloveru@issuu.com",
      "phone": "9141298778"
    },
    {
      "id": "073af6ed-b146-4393-90b1-711f5cbad17e",
      "name": "Carolee",
      "username": "cokenfoldv",
      "email": "cbataliniv@slashdot.org",
      "phone": "6725116753"
    },
    {
      "id": "d0e09bec-7734-4288-9744-0461960bf42f",
      "name": "Mitzi",
      "username": "mtrittenw",
      "email": "mbertiew@google.de",
      "phone": "8149403650"
    },
    {
      "id": "bf3c7c4a-1ae0-46eb-b147-b4af06474dcd",
      "name": "Conant",
      "username": "clantiffex",
      "email": "csandiferx@businessweek.com",
      "phone": "6541884782"
    },
    {
      "id": "f78d0450-199f-47dd-9abe-697e234a7f7a",
      "name": "Catha",
      "username": "cskitchy",
      "email": "ckestley@unesco.org",
      "phone": "3731648631"
    },
    {
      "id": "a03ed213-9544-46fc-a87b-5b6795d235ff",
      "name": "Pooh",
      "username": "pdoakz",
      "email": "priehmz@toplist.cz",
      "phone": "2152080446"
    },
    {
      "id": "c7f790c1-4c4b-41d2-a152-ae6f647cd7a2",
      "name": "Kristyn",
      "username": "kskahill10",
      "email": "klicquorish10@nature.com",
      "phone": "2748995602"
    },
    {
      "id": "a9dfdf21-1b4b-4d83-930a-fd17d3c43965",
      "name": "Michel",
      "username": "mdrews11",
      "email": "msparkwell11@slideshare.net",
      "phone": "9593416735"
    },
    {
      "id": "cedb12e6-3f72-4643-b4db-709b1c374a17",
      "name": "Justinian",
      "username": "jdavidy12",
      "email": "jmouse12@dropbox.com",
      "phone": "6775604618"
    },
    {
      "id": "f0e2b14b-7ae0-4c61-9add-6ff21d0a71ab",
      "name": "Dolph",
      "username": "dfanshaw13",
      "email": "dolle13@squarespace.com",
      "phone": "4161098513"
    },
    {
      "id": "d2afef14-c3f2-425c-805f-22d79a1eae05",
      "name": "Elisha",
      "username": "etummons14",
      "email": "egodsmark14@sogou.com",
      "phone": "2619145588"
    },
    {
      "id": "e35e926f-0a83-4712-a389-f998653ee27c",
      "name": "Kerr",
      "username": "klodden15",
      "email": "kbevens15@loc.gov",
      "phone": "9576221189"
    },
    {
      "id": "4427cc2d-1929-4347-8168-fb43fcb4ae89",
      "name": "Dorothee",
      "username": "dkennelly16",
      "email": "dhenke16@bizjournals.com",
      "phone": "4322496749"
    },
    {
      "id": "66d67435-fca8-4df1-ba46-c5c330281d94",
      "name": "Clayton",
      "username": "cshayler17",
      "email": "correy17@who.int",
      "phone": "5844145759"
    },
    {
      "id": "caf33f31-52c1-4fad-90a9-269b95b52b69",
      "name": "Carmel",
      "username": "cryson18",
      "email": "cnoen18@chronoengine.com",
      "phone": "1778912178"
    },
    {
      "id": "4b2f9d1b-e6c8-4279-940e-c895db6cf5ec",
      "name": "Flossy",
      "username": "fnaton19",
      "email": "fbaume19@aboutads.info",
      "phone": "4088831664"
    },
    {
      "id": "56154927-5708-4e92-a080-c7996cc45872",
      "name": "Ann",
      "username": "aclemenson1a",
      "email": "acherry1a@gizmodo.com",
      "phone": "2263171721"
    },
    {
      "id": "eb14d703-3afa-4432-b8d1-6d0c4a0de384",
      "name": "Elly",
      "username": "emagauran1b",
      "email": "erama1b@wikia.com",
      "phone": "9496152563"
    },
    {
      "id": "8ff33b33-b46d-42e2-9da4-3e981ca93501",
      "name": "Torrance",
      "username": "tpittendreigh1c",
      "email": "tbarczynski1c@list-manage.com",
      "phone": "9131178394"
    },
    {
      "id": "32971239-0f2e-4f9c-8d60-007339a938e1",
      "name": "Hazel",
      "username": "hbritnell1d",
      "email": "hragsdall1d@example.com",
      "phone": "9364129824"
    },
    {
      "id": "af1dc97e-8772-4d89-9a89-eec71670b34a",
      "name": "Marshal",
      "username": "mhexham1e",
      "email": "mpollock1e@slashdot.org",
      "phone": "6051448751"
    },
    {
      "id": "90e0d056-3575-44e5-a3f8-2164b8a3a124",
      "name": "Billy",
      "username": "badolthine1f",
      "email": "bvancastele1f@usnews.com",
      "phone": "2436382486"
    },
    {
      "id": "3f0e3d6a-1bbd-43c0-ba04-44bc2d14bf17",
      "name": "Dredi",
      "username": "dvescovo1g",
      "email": "dhasney1g@thetimes.co.uk",
      "phone": "2991551255"
    },
    {
      "id": "5af6e33d-ad27-4719-86e0-694867bbe8a1",
      "name": "Cristina",
      "username": "cfletcher1h",
      "email": "celan1h@irs.gov",
      "phone": "1008880785"
    },
    {
      "id": "5cfa23b0-9b5c-4a56-8041-b29b68b04867",
      "name": "Mab",
      "username": "mcrust1i",
      "email": "mluney1i@twitpic.com",
      "phone": "5314185968"
    },
    {
      "id": "414061ff-399a-40a6-9128-63964e58cd7b",
      "name": "Etti",
      "username": "ekwietek1j",
      "email": "ekrishtopaittis1j@amazonaws.com",
      "phone": "2132776383"
    },
    {
      "id": "7a688475-adf4-42ac-bfe9-91a2f9342414",
      "name": "Harmony",
      "username": "hwadly1k",
      "email": "hsalmons1k@walmart.com",
      "phone": "7209376770"
    },
    {
      "id": "675fb9d7-533b-48aa-bfd4-14be7ac2d645",
      "name": "Sonnnie",
      "username": "sbrewood1l",
      "email": "spaulino1l@51.la",
      "phone": "8353698917"
    },
    {
      "id": "ae330699-fc11-4568-a3c5-2b43d14a611d",
      "name": "Elianora",
      "username": "egawkes1m",
      "email": "efellibrand1m@psu.edu",
      "phone": "5502351577"
    },
    {
      "id": "f6fdc131-a4b1-4ac6-b0f5-f4bbeb0ab668",
      "name": "Sophronia",
      "username": "slewsy1n",
      "email": "svasilmanov1n@fda.gov",
      "phone": "1185682901"
    },
    {
      "id": "9ca5b6c9-e936-44dd-b3e4-d1d764e2b5c6",
      "name": "Natassia",
      "username": "nglidden1o",
      "email": "ndahlman1o@people.com.cn",
      "phone": "7779364234"
    },
    {
      "id": "7e681797-1e07-4e98-aadb-67acc9a1670e",
      "name": "Cherry",
      "username": "crockingham1p",
      "email": "cbelvin1p@engadget.com",
      "phone": "1123959245"
    },
    {
      "id": "7a467ba1-dc26-4f28-85cf-828ae3051ef1",
      "name": "Ammamaria",
      "username": "agorriessen1q",
      "email": "awilloughey1q@sakura.ne.jp",
      "phone": "8809815353"
    },
    {
      "id": "47f60cc0-08dc-4113-b7d6-5b63027c6cec",
      "name": "Miller",
      "username": "mcraven1r",
      "email": "mdadamo1r@ftc.gov",
      "phone": "1266477251"
    },
    {
      "id": "974ef746-9126-4504-881e-16b3aa200d14",
      "name": "Stanton",
      "username": "ssheather1s",
      "email": "smeneghelli1s@sphinn.com",
      "phone": "4602927800"
    },
    {
      "id": "2c1005df-8a86-4127-8e1a-ae76c62824c0",
      "name": "Glyn",
      "username": "gallner1t",
      "email": "gpacher1t@icio.us",
      "phone": "3785532992"
    },
    {
      "id": "4d027886-44c5-4127-825e-21d753435a05",
      "name": "Pauline",
      "username": "pjerrard1u",
      "email": "pmaudett1u@privacy.gov.au",
      "phone": "9374906756"
    },
    {
      "id": "14a34681-01fe-4af8-8ba2-19670e9b30be",
      "name": "Emlynn",
      "username": "eclempton1v",
      "email": "eedmott1v@yahoo.co.jp",
      "phone": "3608067669"
    },
    {
      "id": "13e014ac-8b65-4795-9c41-fb4334a9d317",
      "name": "Inge",
      "username": "igeeves1w",
      "email": "igouldthorpe1w@umich.edu",
      "phone": "6335589676"
    },
    {
      "id": "b1b2bf7d-a29f-4931-b776-33e65eaeb436",
      "name": "Currie",
      "username": "cmcfayden1x",
      "email": "cascough1x@nsw.gov.au",
      "phone": "1399372291"
    },
    {
      "id": "6dbb9972-d145-4d37-89fe-d9a9ac98c2a1",
      "name": "Marlin",
      "username": "mgambrell1y",
      "email": "mpibsworth1y@yandex.ru",
      "phone": "7393955483"
    },
    {
      "id": "a8162f8b-7c8f-4892-91f6-f8987f03e5d7",
      "name": "Teodoro",
      "username": "tmundee1z",
      "email": "tguthrum1z@reddit.com",
      "phone": "7783193894"
    },
    {
      "id": "0a344c75-d299-47d1-8648-bc970fae7e4e",
      "name": "Olivette",
      "username": "oaleksankin20",
      "email": "oseller20@pagesperso-orange.fr",
      "phone": "6077351814"
    },
    {
      "id": "6006cfbe-285c-48fb-83db-9f72e732ab09",
      "name": "Selestina",
      "username": "squirke21",
      "email": "sbletsoe21@theatlantic.com",
      "phone": "3143407536"
    },
    {
      "id": "43ea4b5d-6d66-43f2-8ccf-58c057964259",
      "name": "Modestine",
      "username": "mmarzello23",
      "email": "myateman23@google.co.jp",
      "phone": "7994542635"
    },
    {
      "id": "baac1435-37fd-4eed-bab0-96ee72f8f252",
      "name": "Vere",
      "username": "vlode24",
      "email": "vkillough24@amazon.co.uk",
      "phone": "2037199969"
    },
    {
      "id": "f6d810b0-311d-41a5-aa31-29282d3a57c3",
      "name": "Cross",
      "username": "croast25",
      "email": "cmarval25@last.fm",
      "phone": "9549911834"
    },
    {
      "id": "1cfbd4a1-04e3-4d4c-8c93-6d14992eab0b",
      "name": "Caddric",
      "username": "cshatliffe26",
      "email": "ckigelman26@spiegel.de",
      "phone": "8936744304"
    },
    {
      "id": "5ae48c26-b91c-4192-9061-ffd153e1822c",
      "name": "Mendie",
      "username": "mblyth27",
      "email": "mcordelette27@aboutads.info",
      "phone": "7862625603"
    },
    {
      "id": "ff831060-9e59-4507-9c40-830b6b48c66e",
      "name": "Emmett",
      "username": "ehuntly28",
      "email": "edorr28@g.co",
      "phone": "6691445434"
    },
    {
      "id": "3ba2de9f-5ff6-4bb7-bb4f-ade950d0afef",
      "name": "Reider",
      "username": "rviccary29",
      "email": "rknewstub29@cnn.com",
      "phone": "7174175050"
    },
    {
      "id": "88b54014-e9f5-4805-aa2d-feb6fd3acf2c",
      "name": "Trenton",
      "username": "thovee2a",
      "email": "toboyle2a@cargocollective.com",
      "phone": "5956861947"
    },
    {
      "id": "c343d176-3abc-40c8-a624-3fdfedf3116f",
      "name": "Ned",
      "username": "nhazeman2b",
      "email": "nmaylin2b@reuters.com",
      "phone": "7961228092"
    },
    {
      "id": "efd67465-2af3-43bb-a8f9-87b882479aad",
      "name": "Carmen",
      "username": "cyeandel2c",
      "email": "ctaborre2c@mtv.com",
      "phone": "1765425395"
    },
    {
      "id": "4afb62f7-e6cb-4a79-b440-809f4496b2d6",
      "name": "Erin",
      "username": "ebellenger2d",
      "email": "epomphrey2d@amazonaws.com",
      "phone": "3058370755"
    },
    {
      "id": "a13f5466-76ce-45fe-8061-bcbd58acf973",
      "name": "Vite",
      "username": "vchristophle2e",
      "email": "vgudeman2e@histats.com",
      "phone": "1399482371"
    },
    {
      "id": "8dada3aa-de33-4cdf-a508-c69b3db3518f",
      "name": "Immanuel",
      "username": "igambrell2f",
      "email": "ishoebrook2f@t-online.de",
      "phone": "9959848140"
    },
    {
      "id": "a947a258-bbbb-4f6f-9a37-54814b343d7e",
      "name": "Eal",
      "username": "evinnicombe2g",
      "email": "edurnall2g@mail.ru",
      "phone": "6565017237"
    },
    {
      "id": "50946eca-bdf0-44f2-9593-14e4ec09e52d",
      "name": "Ursulina",
      "username": "usilvers2h",
      "email": "uthickett2h@yellowpages.com",
      "phone": "3374706214"
    },
    {
      "id": "dd38d255-292a-4ac1-95d4-e9c678aeeedf",
      "name": "Robbert",
      "username": "raxtens2i",
      "email": "rtreadgold2i@mediafire.com",
      "phone": "1134867034"
    },
    {
      "id": "81c1bfad-85aa-4587-9f19-79f111580156",
      "name": "Kerrin",
      "username": "kespinel2j",
      "email": "kminghetti2j@wunderground.com",
      "phone": "6273149256"
    },
    {
      "id": "5bc3e707-c5b7-4fe3-9d0e-92557595488a",
      "name": "Max",
      "username": "mduffill2k",
      "email": "mdanne2k@earthlink.net",
      "phone": "5754359809"
    },
    {
      "id": "41847f42-7eae-4ee4-bd72-b13bbb2a21f5",
      "name": "Birk",
      "username": "bleal2l",
      "email": "balhirsi2l@phpbb.com",
      "phone": "9328217273"
    },
    {
      "id": "439f709e-55ce-4600-ae69-8b01f4c69281",
      "name": "Shir",
      "username": "sscargill2m",
      "email": "srobens2m@ted.com",
      "phone": "8855630925"
    },
    {
      "id": "2a88454c-7b2d-45fd-a704-5031bb13d287",
      "name": "Douglass",
      "username": "dgolt2n",
      "email": "dlinstead2n@jimdo.com",
      "phone": "4991335295"
    },
    {
      "id": "b9cc6051-5753-4950-99ef-fed593bef992",
      "name": "Valencia",
      "username": "vthorntondewhirst2o",
      "email": "vrouthorn2o@cbsnews.com",
      "phone": "7538895541"
    },
    {
      "id": "d13df123-16d5-4810-887c-e88d7e8deed6",
      "name": "Nathaniel",
      "username": "nmegroff2p",
      "email": "njeffery2p@jimdo.com",
      "phone": "3278739500"
    },
    {
      "id": "dcc7dc04-696e-4a74-a496-e8a46aecb5cb",
      "name": "Bernita",
      "username": "bguerola2q",
      "email": "bsamms2q@cornell.edu",
      "phone": "5764357452"
    },
    {
      "id": "1cb5b77a-7f47-466e-982c-d7ab48cd5269",
      "name": "Diann",
      "username": "dgodsmark2r",
      "email": "dwellington2r@jugem.jp",
      "phone": "9395290700"
    },
    {
      "id": "a8pNhDXF4AUc0kxfWJhnr",
      "name": "Prathipa",
      "username": "mprathipa",
      "email": "prathipa@gmail.com",
      "phone": "88853779"
    }
  ]
}